[{"name":"BESNİ","code":"1182","cityName":"ADIYAMAN","cityCode":"02"},{"name":"ÇELİKHAN","code":"1246","cityName":"ADIYAMAN","cityCode":"02"},{"name":"GERGER","code":"1347","cityName":"ADIYAMAN","cityCode":"02"},{"name":"GÖLBAŞI","code":"1354","cityName":"ADIYAMAN","cityCode":"02"},{"name":"KAHTA","code":"1425","cityName":"ADIYAMAN","cityCode":"02"},{"name":"MERKEZ","code":"1105","cityName":"ADIYAMAN","cityCode":"02"},{"name":"SAMSAT","code":"1592","cityName":"ADIYAMAN","cityCode":"02"},{"name":"SİNCİK","code":"1985","cityName":"ADIYAMAN","cityCode":"02"},{"name":"TUT","code":"1989","cityName":"ADIYAMAN","cityCode":"02"}]
