[{"name":"ENEZ","code":"1307","cityName":"EDİRNE","cityCode":"22"},{"name":"HAVSA","code":"1385","cityName":"EDİRNE","cityCode":"22"},{"name":"İPSALA","code":"1412","cityName":"EDİRNE","cityCode":"22"},{"name":"KEŞAN","code":"1464","cityName":"EDİRNE","cityCode":"22"},{"name":"LALAPAŞA","code":"1502","cityName":"EDİRNE","cityCode":"22"},{"name":"MERİÇ","code":"1523","cityName":"EDİRNE","cityCode":"22"},{"name":"MERKEZ","code":"1295","cityName":"EDİRNE","cityCode":"22"},{"name":"SÜLOĞLU","code":"1988","cityName":"EDİRNE","cityCode":"22"},{"name":"UZUNKÖPRÜ","code":"1705","cityName":"EDİRNE","cityCode":"22"}]
